oscclip/__init__.py
oscclip-0.4.1.dist-info/entry_points.txt
oscclip-0.4.1.dist-info/LICENSE
oscclip-0.4.1.dist-info/WHEEL
oscclip-0.4.1.dist-info/METADATA
oscclip-0.4.1.dist-info/RECORD
