Metadata-Version: 2.1
Name: oscclip
Version: 0.4.1
Summary: Utilities to access the clipboard via OSC52
Home-page: https://github.com/rumpelsepp/oscclip
License: GPLv3
Author: Stefan Tatschner
Author-email: stefan@rumpelsepp.org
Requires-Python: >=3.10,<4.0
Classifier: License :: Other/Proprietary License
Classifier: Programming Language :: Python :: 3
Classifier: Programming Language :: Python :: 3.10
Project-URL: Repository, https://github.com/rumpelsepp/oscclip
